subclip.py
Subclip-0.0.2.dist-info/LICENSE.txt
Subclip-0.0.2.dist-info/METADATA
Subclip-0.0.2.dist-info/WHEEL
Subclip-0.0.2.dist-info/top_level.txt
Subclip-0.0.2.dist-info/RECORD
