Metadata-Version: 2.1
Name: Subclip
Version: 0.0.2
Summary: A package to make NLP easy, fast, and fun
Home-page: UNKNOWN
Author: Hyeonwook Kang
License: UNKNOWN
Platform: UNKNOWN
Classifier: Programming Language :: Python :: 3
Classifier: License :: OSI Approved :: MIT License
Classifier: Operating System :: OS Independent
Requires-Python: >=3.6
License-File: LICENSE.txt
